CONTRIBUTORS
LICENSE
MANIFEST.in
Makefile
README.rst
requirements.txt
setup.py
tox.ini
docs/source/conf.py
docs/source/contributing.rst
docs/source/debugging_leak.rst
docs/source/getting_started.rst
docs/source/index.rst
docs/source/security.rst
docs/source/statistics.rst
docs/source/troubleshooting.rst
docs/source/versioning_compatibility.rst
docs/source/api/client.rst
docs/source/api/command.rst
docs/source/api/console.rst
docs/source/api/dispatch.rst
docs/source/api/implant.rst
docs/source/api/index.rst
docs/source/api/ioproxy.rst
docs/source/api/parser.rst
docs/source/api/quitterproxy.rst
docs/source/api/shared.rst
docs/source/api/stats.rst
docs/source/api/stoppable_thread.rst
docs/source/images/clone_link.png
docs/source/images/complete_pull_request.png
docs/source/images/fork_button.png
docs/source/images/memory_usage.svg
docs/source/images/memory_usage_after_fix.svg
docs/source/images/objgraph.png
docs/source/images/personal_repo.png
docs/source/images/pull_request_button.png
docs/source/images/pull_request_form.png
eww/__init__.py
eww/command.py
eww/console.py
eww/dispatch.py
eww/implant.py
eww/ioproxy.py
eww/parser.py
eww/quitterproxy.py
eww/shared.py
eww/stats.py
eww/stoppable_thread.py
eww.egg-info/PKG-INFO
eww.egg-info/SOURCES.txt
eww.egg-info/dependency_links.txt
eww.egg-info/requires.txt
eww.egg-info/top_level.txt
scripts/eww